lusidjam/__init__.py
lusidjam/refreshing_token.py
lusid_jam-0.1.2.dist-info/LICENSE
lusid_jam-0.1.2.dist-info/METADATA
lusid_jam-0.1.2.dist-info/WHEEL
lusid_jam-0.1.2.dist-info/top_level.txt
lusid_jam-0.1.2.dist-info/RECORD
